setup.py
dm/__init__.py
dm.sharedresource.egg-info/PKG-INFO
dm.sharedresource.egg-info/SOURCES.txt
dm.sharedresource.egg-info/dependency_links.txt
dm.sharedresource.egg-info/namespace_packages.txt
dm.sharedresource.egg-info/top_level.txt
dm.sharedresource.egg-info/zip-safe
dm/sharedresource/LICENSE.txt
dm/sharedresource/README.txt
dm/sharedresource/VERSION.txt
dm/sharedresource/__init__.py
dm/sharedresource/tests.py
