Metadata-Version: 1.0
Name: dm.sharedresource
Version: 1.0
Summary: Resources which can safely be used by concurrent threads
Home-page: http://www.dieter.handshake.de/pyprojects/Zope
Author: Dieter Maurer
Author-email: dieter@handshake.de
License: BSD (see "dm/sharedresource/LICENSE.txt", for details)
Keywords: sharedresource
Platform: UNKNOWN
Classifier: Development Status :: 5 - Production/Stable
Classifier: Intended Audience :: Developers
Classifier: License :: OSI Approved :: BSD License
Classifier: Operating System :: OS Independent
Classifier: Programming Language :: Python
Classifier: Topic :: Software Development
Classifier: Topic :: Utilities
